LICENSE
MANIFEST.in
README.rst
requirements.txt
setup.py
django_xliff.egg-info/PKG-INFO
django_xliff.egg-info/SOURCES.txt
django_xliff.egg-info/dependency_links.txt
django_xliff.egg-info/top_level.txt
doc_src/.DS_Store
doc_src/Makefile
doc_src/conf.py
doc_src/getting_started.rst
doc_src/index.rst
doc_src/make.bat
doc_src/_build/doctrees/environment.pickle
doc_src/_build/doctrees/getting_started.doctree
doc_src/_build/doctrees/index.doctree
doc_src/_build/doctrees/installation.doctree
doc_src/_build/doctrees/reference/comparison.doctree
doc_src/_build/doctrees/reference/index.doctree
doc_src/_build/doctrees/reference/models.doctree
doc_src/_build/doctrees/reference/settings.doctree
doc_src/_static/breadcrumb_background.png
doc_src/_static/default.css
doc_src/_static/documentation.png
doc_src/_static/header_sm_mid.png
doc_src/_static/scrn1.png
doc_src/_static/scrn2.png
doc_src/_static/searchfield_leftcap.png
doc_src/_static/searchfield_repeat.png
doc_src/_static/searchfield_rightcap.png
doc_src/_static/title_background.png
doc_src/_static/toc.js
doc_src/_static/triangle_closed.png
doc_src/_static/triangle_left.png
doc_src/_static/triangle_open.png
doc_src/_templates/layout.html
doc_src/reference/comparison.rst
doc_src/reference/index.rst
doc_src/reference/settings.rst
docs/.buildinfo
docs/genindex.html
docs/getting_started.html
docs/index.html
docs/objects.inv
docs/search.html
docs/searchindex.js
docs/_sources/getting_started.txt
docs/_sources/index.txt
docs/_sources/reference/comparison.txt
docs/_sources/reference/index.txt
docs/_sources/reference/settings.txt
docs/_static/ajax-loader.gif
docs/_static/basic.css
docs/_static/breadcrumb_background.png
docs/_static/comment-bright.png
docs/_static/comment-close.png
docs/_static/comment.png
docs/_static/default.css
docs/_static/doctools.js
docs/_static/documentation.png
docs/_static/down-pressed.png
docs/_static/down.png
docs/_static/file.png
docs/_static/header_sm_mid.png
docs/_static/jquery.js
docs/_static/minus.png
docs/_static/plus.png
docs/_static/pygments.css
docs/_static/scrn1.png
docs/_static/scrn2.png
docs/_static/searchfield_leftcap.png
