Metadata-Version: 1.1
Name: django-xliff
Version: 0.3.2
Summary: XML Localisation Interchange File Format (XLIFF) serializer for Django
Home-page: https://github.com/callowayproject/django-xliff
Author: Corey Oordt
Author-email: coreyoordt@gmail.com
License: UNKNOWN
Platform: UNKNOWN
Classifier: Framework :: Django
